byted_tiktok_session_lite_sdk/__init__.py
byted_tiktok_session_lite_sdk-0.0.1.dist-info/METADATA
byted_tiktok_session_lite_sdk-0.0.1.dist-info/WHEEL
byted_tiktok_session_lite_sdk-0.0.1.dist-info/top_level.txt
byted_tiktok_session_lite_sdk-0.0.1.dist-info/RECORD
