Metadata-Version: 2.1
Name: byted-tiktok-session-lite-sdk
Version: 0.0.1
Summary: A simple package named byted_tiktok_session_lite_sdk
Home-page: https://github.com/artifact/byted_tiktok_session_lite_sdk.git
Author: artifact
Author-email: artifact@example.com
License: UNKNOWN
Platform: UNKNOWN
Classifier: Programming Language :: Python :: 3
Classifier: License :: OSI Approved :: MIT License
Classifier: Operating System :: OS Independent
